affinity.py
affinity-1.1.0.dist-info/METADATA
affinity-1.1.0.dist-info/WHEEL
affinity-1.1.0.dist-info/RECORD
