Metadata-Version: 2.4
Name: affinity
Version: 1.1.0
Summary: Module for creating well-documented datasets, with types and annotations.
Author: Alex Kislukhin
Requires-Python: >=3.11
Requires-Dist: duckdb>=1.3
Requires-Dist: pandas>=2.2
